python_latex/__init__.py
python_latex/compile_tex.py
python_latex/python_latex.py
python_latex/watcher.py
python_latex/__pycache__/compile_tex.cpython-37.pyc
python_latex/__pycache__/watcher.cpython-37.pyc
python_latex-1.0.1.dist-info/LICENSE
python_latex-1.0.1.dist-info/METADATA
python_latex-1.0.1.dist-info/WHEEL
python_latex-1.0.1.dist-info/entry_points.txt
python_latex-1.0.1.dist-info/top_level.txt
python_latex-1.0.1.dist-info/RECORD
