Metadata-Version: 2.1
Name: python-latex
Version: 1.0.1
Summary: Convenience wrappers around latex compilation with python
Home-page: https://github.com/JoshuaNeely/python-latex
Author: Joshua Neely
Author-email: joshua.a.neely@gmail.com
License: UNKNOWN
Platform: UNKNOWN
Classifier: Programming Language :: Python :: 3
Classifier: License :: OSI Approved :: MIT License
Classifier: Operating System :: OS Independent
Requires-Dist: latex
Requires-Dist: watchdog
